[
    {
        "pk": 1,
        "model": "products.product",
        "fields": {
            "sku": "hh001",
            "name": "Large Honey Pot",
            "description": "Large Honey Pot - 500g",
            "price": 53.99,
            "category": 1,
            "rating": 4.6,
            "image": "large-jar.jpg"
        }
    },
    {
        "pk": 2,
        "model": "products.product",
        "fields": {
            "sku": "hh002",
            "name": "Small Honey Pot",
            "description": "Small Honey Pot - 250g",
            "price": 53.99,
            "category": 1,
            "rating": 4.6,
            "image": "small-jar.jpg"
        }
    },
    {
        "pk": 3,
        "model": "products.product",
        "fields": {
            "sku": "hh003",
            "name": "Large Honey Pot and Spoon",
            "description": "Large Honey Pot - 250g with honey spoon bundle",
            "price": 53.99,
            "category": 1,
            "rating": 4.6,
            "image": "honey-jar-spoon.jpg"
        }
    },
    {
        "pk": 4,
        "model": "products.product",
        "fields": {
            "sku": "hh004",
            "name": "Small Honey Pot with Spoon",
            "description": "Small Honey Pot - 250g with honey spoon bundle",
            "price": 53.99,
            "category": 1,
            "rating": 4.6,
            "image": "honey-jar-spoon.jpg"
        }
    },
    {
        "pk": 5,
        "model": "products.product",
        "fields": {
            "sku": "hh005",
            "name": "Honey Spoon",
            "description": "Waste no honey with our wooden honey spoon!",
            "price": 53.99,
            "category": 4,
            "rating": 4.6,
            "image": "honey-spoon.jpg"
        }
    },
    {
        "pk": 6,
        "model": "products.product",
        "fields": {
            "sku": "hh006",
            "name": "Bee-Keeper suit",
            "description": "Keep yourself protected with our bee-keeping suit",
            "price": 53.99,
            "category": 3,
            "rating": 4.6,
            "image": "beekeeper-suit.jpg"
        }
    },
    {
        "pk": 7,
        "model": "products.product",
        "fields": {
            "sku": "hh007",
            "name": "Bee Balm",
            "description": "Keep your lips hydrated with our organic lip balm",
            "price": 53.99,
            "category": 5,
            "rating": 4.6,
            "image": "bee-balm.jpg"
        }
    },
    {
        "pk": 8,
        "model": "products.product",
        "fields": {
            "sku": "hh008",
            "name": "Bee's Wax Candle",
            "description": "Light up your night with our Organic candles",
            "price": 53.99,
            "category": 5,
            "rating": 4.6,
            "image": "bee-candle.jpg"
        }
    },
    {
        "pk": 9,
        "model": "products.product",
        "fields": {
            "sku": "hh009",
            "name": "Bee's Wax Wrap",
            "description": "Keep your items sealed longer with our organic bee wrap",
            "price": 53.99,
            "category": 5,
            "rating": 4.6,
            "image": "beewax-wrap.jpg"
        }
    },
    {
        "pk": 10,
        "model": "products.product",
        "fields": {
            "sku": "hh010",
            "name": "Honeycomb Frame",
            "description": "Honeycomb starter frame for your hives",
            "price": 53.99,
            "category": 3,
            "rating": 4.6,
            "image": "honey-frame.jpg"
        }
    },
    {
        "pk": 11,
        "model": "products.product",
        "fields": {
            "sku": "hh011",
            "name": "Bee Hive Tower",
            "description": "Bee Hive to store all your hard working bees",
            "price": 53.99,
            "category": 3,
            "rating": 4.6,
            "image": "honey-frame.jpg"
        }
    },
    {
        "pk": 12,
        "model": "products.product",
        "fields": {
            "sku": "hh012",
            "name": "Tea Mug",
            "description": "Bee graphic Mug",
            "price": 53.99,
            "category": 4,
            "rating": 4.6,
            "image": "bee-merch.jpg"
        }
    },
    {
        "pk": 13,
        "model": "products.product",
        "fields": {
            "sku": "hh013",
            "name": "Bee Key-chain",
            "description": "Keychain with Bee graphic",
            "price": 53.99,
            "category": 4,
            "rating": 4.6,
            "image": "bee-merch.jpg"
        }
    },
    {
        "pk": 14,
        "model": "products.product",
        "fields": {
            "sku": "hh014",
            "name": "Baseball Bee Cap",
            "description": "Baseball cap with Bee graphic",
            "price": 53.99,
            "category": 2,
            "rating": 4.6,
            "image": "bee-merch.jpg"
        }
    },
    {
        "pk": 15,
        "model": "products.product",
        "fields": {
            "sku": "hh015",
            "name": "T-shirts",
            "description": "T-shirts with Bee graphic",
            "price": 53.99,
            "category": 2,
            "rating": 4.6,
            "image": "bee-merch.jpg"
        }
    },
    {
        "pk": 15,
        "model": "products.product",
        "fields": {
            "sku": "hh015",
            "name": "Bee graphic Bottle",
            "description": "Bottle (500ml) with Bee graphic",
            "price": 53.99,
            "category": 4,
            "rating": 4.6,
            "image": "bee-merch.jpg"
        }
    }
   
]